sophy.cpython-39-x86_64-linux-gnu.so
sophy-0.6.5.dist-info/METADATA
sophy-0.6.5.dist-info/WHEEL
sophy-0.6.5.dist-info/top_level.txt
sophy-0.6.5.dist-info/RECORD
sophy-0.6.5.dist-info/licenses/LICENSE
