Metadata-Version: 2.4
Name: sophy
Version: 0.6.5
Summary: fast bindings for the sophia database
Author-email: Charles Leifer <coleifer@gmail.com>
Project-URL: Repository, https://github.com/coleifer/sophy
Project-URL: Documentation, https://sophy.readthedocs.io/
Classifier: Programming Language :: Python :: 2
Classifier: Programming Language :: Python :: 3
Classifier: Topic :: Software Development :: Libraries :: Python Modules
License-File: LICENSE
Dynamic: license-file
